tree_sitter_solidity/__init__.py
tree_sitter_solidity/__init__.pyi
tree_sitter_solidity/_binding.abi3.so
tree_sitter_solidity/binding.c
tree_sitter_solidity/py.typed
tree_sitter_solidity/queries/highlights-nvim.scm
tree_sitter_solidity/queries/highlights.scm
tree_sitter_solidity/queries/locals.scm
tree_sitter_solidity/queries/tags.scm
tree_sitter_solidity-1.2.13.dist-info/METADATA
tree_sitter_solidity-1.2.13.dist-info/WHEEL
tree_sitter_solidity-1.2.13.dist-info/top_level.txt
tree_sitter_solidity-1.2.13.dist-info/RECORD
tree_sitter_solidity-1.2.13.dist-info/licenses/LICENSE
