Metadata-Version: 2.4
Name: tree-sitter-solidity
Version: 1.2.13
Summary: Solidity grammar for tree-sitter
Author: Joran Honig
License: MIT
Project-URL: Homepage, https://github.com/JoranHonig/tree-sitter-solidity
Keywords: incremental,parsing,tree-sitter,solidity
Classifier: Intended Audience :: Developers
Classifier: License :: OSI Approved :: MIT License
Classifier: Topic :: Software Development :: Compilers
Classifier: Topic :: Text Processing :: Linguistic
Classifier: Typing :: Typed
Requires-Python: >=3.9
License-File: LICENSE
Provides-Extra: core
Requires-Dist: tree-sitter~=0.22; extra == "core"
Dynamic: license-file
